{
  "name": "videos/fixed-video-id.mp4",
  "bucket": "fake-id-is-inserted-as-it-is-needed-for-the-emulator.appspot.com",
  "metageneration": 1,
  "generation": 1676966340449,
  "contentType": "application/octet-stream",
  "storageClass": "STANDARD",
  "contentDisposition": "inline",
  "downloadTokens": [
    "932fd644-36c2-45c0-997c-502b19c10f3c"
  ],
  "etag": "PugNoE0OmYyTlPli1AGsqXPN10k",
  "customMetadata": {},
  "timeCreated": "2023-02-21T07:59:00.449Z",
  "updated": "2023-02-21T07:59:00.449Z",
  "size": 10876456,
  "md5Hash": "Jnsrv8jLqEPKl4Dk4scgPA==",
  "crc32c": "4204453997"
}